{"stats":{"minecraft:mined":{"minecraft:dark_oak_planks":6,"minecraft:blue_carpet":11,"minecraft:white_bed":16,"minecraft:jungle_leaves":18,"minecraft:obsidian":40,"minecraft:granite":381,"minecraft:jungle_log":17,"minecraft:light_gray_bed":9,"minecraft:blue_wool":1,"minecraft:oak_wall_sign":11,"minecraft:oxeye_daisy":15,"minecraft:chiseled_stone_bricks":1,"minecraft:spawner":1,"minecraft:magma_block":18,"minecraft:pumpkin":23,"minecraft:enchanting_table":2,"minecraft:spruce_pressure_plate":16,"minecraft:blue_orchid":7,"minecraft:white_banner":4,"minecraft:tripwire":11,"minecraft:brown_mushroom":14,"minecraft:red_bed":12,"minecraft:kelp_plant":24,"minecraft:torch":22,"minecraft:note_block":2,"minecraft:blast_furnace":1,"minecraft:melon":1,"minecraft:glass":6,"minecraft:sugar_cane":180,"minecraft:bricks":2,"minecraft:birch_sapling":1,"minecraft:repeater":3,"minecraft:wheat":464,"minecraft:jukebox":1,"minecraft:pumpkin_stem":5,"minecraft:stone_brick_stairs":5,"minecraft:grass":305,"minecraft:oak_fence_gate":6,"minecraft:loom":1,"minecraft:stonecutter":1,"minecraft:piston":2,"minecraft:attached_pumpkin_stem":2,"minecraft:sea_lantern":2,"minecraft:dark_oak_fence":15,"minecraft:allium":2,"minecraft:spruce_fence":14,"minecraft:jungle_planks":10,"minecraft:redstone_wire":242,"minecraft:cartography_table":1,"minecraft:red_mushroom":2,"minecraft:kelp":22,"minecraft:redstone_ore":149,"minecraft:andesite":572,"minecraft:potatoes":83,"minecraft:cobblestone_slab":25,"minecraft:vine":34,"minecraft:rail":73,"minecraft:bamboo_sapling":3,"minecraft:bamboo":16,"minecraft:light_gray_carpet":28,"minecraft:redstone_block":1,"minecraft:glass_pane":6,"minecraft:observer":2,"minecraft:dandelion":16,"minecraft:cornflower":6,"minecraft:spruce_button":8,"minecraft:dropper":4,"minecraft:diorite":144,"minecraft:white_carpet":25,"minecraft:spruce_log":271,"minecraft:birch_leaves":107,"minecraft:gravel":124,"minecraft:cobweb":2,"minecraft:oak_button":4,"minecraft:stone_bricks":21,"minecraft:gold_ore":108,"minecraft:fern":85,"minecraft:spruce_planks":29,"minecraft:farmland":1,"minecraft:jungle_slab":2,"minecraft:cobblestone_stairs":24,"minecraft:spruce_trapdoor":4,"minecraft:grass_block":943,"minecraft:gray_banner":4,"minecraft:polished_diorite":4,"minecraft:composter":2,"minecraft:glowstone":54,"minecraft:iron_ore":447,"minecraft:azure_bluet":30,"minecraft:dark_oak_stairs":1,"minecraft:red_tulip":1,"minecraft:spruce_slab":15,"minecraft:clay":50,"minecraft:jungle_stairs":4,"minecraft:poppy":21,"minecraft:chest":16,"minecraft:nether_quartz_ore":69,"minecraft:cobblestone":991,"minecraft:oak_planks":20,"minecraft:wall_torch":181,"minecraft:cauldron":1,"minecraft:seagrass":17,"minecraft:powered_rail":3,"minecraft:birch_log":106,"minecraft:birch_trapdoor":4,"minecraft:orange_tulip":1,"minecraft:oak_log":321,"minecraft:beetroots":22,"minecraft:diorite_wall":4,"minecraft:sand":528,"minecraft:dirt":1576,"minecraft:tripwire_hook":4,"minecraft:dispenser":4,"minecraft:netherrack":154,"minecraft:oak_leaves":610,"minecraft:daylight_detector":3,"minecraft:diamond_ore":19,"minecraft:lever":14,"minecraft:ladder":19,"minecraft:spruce_leaves":155,"minecraft:sandstone":61,"minecraft:oak_trapdoor":5,"minecraft:furnace":14,"minecraft:carrots":202,"minecraft:stripped_spruce_log":14,"minecraft:bookshelf":10,"minecraft:lantern":2,"minecraft:stripped_oak_log":2,"minecraft:packed_ice":51,"minecraft:stone":5201,"minecraft:redstone_wall_torch":2,"minecraft:scaffolding":7,"minecraft:polished_granite":8,"minecraft:oak_fence":100,"minecraft:crafting_table":18,"minecraft:andesite_wall":9,"minecraft:lapis_ore":25,"minecraft:lily_pad":1,"minecraft:spruce_stairs":8,"minecraft:gray_wool":2,"minecraft:redstone_torch":2,"minecraft:sweet_berry_bush":35,"minecraft:ice":35,"minecraft:white_wall_banner":1,"minecraft:grass_path":5,"minecraft:coal_ore":707,"minecraft:cocoa":6,"minecraft:gray_carpet":14,"minecraft:cracked_stone_bricks":5,"minecraft:polished_andesite":7,"minecraft:mossy_stone_bricks":10},"minecraft:killed_by":{"minecraft:pillager":1,"minecraft:ravager":1,"minecraft:zombie":6,"minecraft:creeper":7,"minecraft:drowned":1,"minecraft:witch":1,"minecraft:spider":2,"minecraft:skeleton":11},"minecraft:dropped":{"minecraft:iron_sword":11,"minecraft:lapis_lazuli":12,"minecraft:cooked_beef":32,"minecraft:glass_bottle":8,"minecraft:cooked_porkchop":3,"minecraft:saddle":1,"minecraft:red_mushroom":4,"minecraft:dirt":106,"minecraft:red_bed":3,"minecraft:dark_oak_fence":2,"minecraft:yellow_dye":1,"minecraft:bone_meal":32,"minecraft:sunflower":3,"minecraft:sand":12,"minecraft:sugar":2,"minecraft:iron_pickaxe":9,"minecraft:dark_oak_planks":3,"minecraft:bone":3,"minecraft:stone_axe":3,"minecraft:sugar_cane":7,"minecraft:golden_chestplate":1,"minecraft:wheat":22,"minecraft:blue_wool":1,"minecraft:rotten_flesh":135,"minecraft:oak_planks":6,"minecraft:light_gray_carpet":35,"minecraft:azure_bluet":5,"minecraft:white_bed":2,"minecraft:salmon":7,"minecraft:rabbit_foot":11,"minecraft:ladder":3,"minecraft:glass":1,"minecraft:egg":6,"minecraft:enchanted_book":3,"minecraft:golden_boots":2,"minecraft:iron_ingot":1,"minecraft:wheat_seeds":200,"minecraft:iron_helmet":1,"minecraft:oak_fence":65,"minecraft:feather":2,"minecraft:cobblestone":956,"minecraft:apple":10,"minecraft:granite":37,"minecraft:spruce_button":5,"minecraft:coal":25,"minecraft:jungle_slab":2,"minecraft:ink_sac":1,"minecraft:wooden_axe":1,"minecraft:rabbit":1,"minecraft:cooked_salmon":1,"minecraft:red_dye":2,"minecraft:paper":148,"minecraft:string":2,"minecraft:spruce_sapling":1,"minecraft:stone_sword":9,"minecraft:chicken":2,"minecraft:white_carpet":2,"minecraft:iron_boots":1,"minecraft:name_tag":3,"minecraft:oak_sign":1,"minecraft:spruce_fence":2,"minecraft:pumpkin_seeds":20,"minecraft:diamond_sword":3,"minecraft:potato":9,"minecraft:spruce_planks":4,"minecraft:diamond_pickaxe":1,"minecraft:wooden_shovel":2,"minecraft:spider_eye":10,"minecraft:stone_bricks":33,"minecraft:light_gray_dye":9,"minecraft:bow":3,"minecraft:magenta_dye":1,"minecraft:birch_planks":12,"minecraft:brown_mushroom":11,"minecraft:dark_oak_stairs":1,"minecraft:leather":2,"minecraft:jungle_planks":32,"minecraft:flint":1,"minecraft:cobblestone_stairs":9,"minecraft:mutton":4,"minecraft:birch_log":2,"minecraft:gravel":3,"minecraft:cooked_mutton":21,"minecraft:carrot":63,"minecraft:poppy":8,"minecraft:beetroot_seeds":7,"minecraft:birch_door":1,"minecraft:chest":1,"minecraft:iron_ore":2,"minecraft:arrow":22,"minecraft:scaffolding":1,"minecraft:stone_hoe":1,"minecraft:bread":2,"minecraft:golden_helmet":2,"minecraft:bookshelf":2,"minecraft:poisonous_potato":3,"minecraft:spruce_stairs":2,"minecraft:stick":40,"minecraft:diorite":25,"minecraft:torch":16,"minecraft:iron_leggings":2,"minecraft:iron_axe":2,"minecraft:bucket":1,"minecraft:dandelion":3,"minecraft:kelp":15,"minecraft:sweet_berries":57,"minecraft:iron_hoe":1,"minecraft:glass_pane":15,"minecraft:filled_map":7,"minecraft:shield":1,"minecraft:iron_chestplate":4,"minecraft:andesite":125,"minecraft:light_gray_bed":1,"minecraft:oak_boat":1,"minecraft:golden_leggings":1,"minecraft:oak_sapling":9,"minecraft:stone_pickaxe":9},"minecraft:crafted":{"minecraft:jungle_button":1,"minecraft:black_dye":1,"minecraft:oak_sign":15,"minecraft:loom":1,"minecraft:lever":5,"minecraft:bookshelf":16,"minecraft:cooked_mutton":33,"minecraft:glass":130,"minecraft:repeater":1,"minecraft:melon_seeds":4,"minecraft:iron_door":3,"minecraft:birch_door":3,"minecraft:magenta_dye":8,"minecraft:name_tag":1,"minecraft:cooked_rabbit":6,"minecraft:glass_bottle":3,"minecraft:redstone_lamp":1,"minecraft:wooden_shovel":2,"minecraft:emerald":12,"minecraft:cooked_porkchop":31,"minecraft:spruce_door":12,"minecraft:smithing_table":1,"minecraft:golden_pickaxe":2,"minecraft:clock":6,"minecraft:sticky_piston":1,"minecraft:hay_block":2,"minecraft:campfire":1,"minecraft:painting":2,"minecraft:cartography_table":1,"minecraft:light_gray_bed":1,"minecraft:golden_leggings":1,"minecraft:compass":3,"minecraft:iron_pickaxe":29,"minecraft:iron_block":3,"minecraft:gold_ingot":109,"minecraft:light_gray_dye":25,"minecraft:composter":1,"minecraft:spruce_fence_gate":2,"minecraft:stone_shovel":2,"minecraft:jukebox":1,"minecraft:iron_nugget":9,"minecraft:bone_meal":117,"minecraft:spruce_fence":93,"minecraft:white_carpet":35,"minecraft:pink_dye":2,"minecraft:andesite_wall":30,"minecraft:lantern":1,"minecraft:spruce_stairs":4,"minecraft:ladder":630,"minecraft:spruce_slab":18,"minecraft:stone_pickaxe":24,"minecraft:spruce_boat":2,"minecraft:redstone_block":27,"minecraft:lead":4,"minecraft:golden_helmet":1,"minecraft:daylight_detector":1,"minecraft:enchanting_table":1,"minecraft:red_bed":1,"minecraft:polished_granite":44,"minecraft:dark_oak_button":1,"minecraft:glowstone":3,"minecraft:orange_dye":5,"minecraft:oak_fence_gate":6,"minecraft:birch_trapdoor":6,"minecraft:writable_book":3,"minecraft:iron_shovel":3,"minecraft:iron_leggings":2,"minecraft:white_bed":5,"minecraft:note_block":2,"minecraft:blue_carpet":14,"minecraft:brick":184,"minecraft:oak_planks":1064,"minecraft:cobblestone_slab":24,"minecraft:leather_horse_armor":1,"minecraft:cooked_chicken":20,"minecraft:cobblestone_stairs":28,"minecraft:stone":231,"minecraft:flower_banner_pattern":1,"minecraft:spruce_pressure_plate":11,"minecraft:bow":4,"minecraft:iron_boots":1,"minecraft:chest":19,"minecraft:oak_button":1,"minecraft:bricks":46,"minecraft:stone_hoe":2,"minecraft:oak_fence":75,"minecraft:golden_sword":1,"minecraft:golden_boots":1,"minecraft:smoker":1,"minecraft:white_banner":2,"minecraft:dropper":1,"minecraft:item_frame":3,"minecraft:arrow":24,"minecraft:cauldron":2,"minecraft:map":2,"minecraft:crafting_table":12,"minecraft:spruce_planks":948,"minecraft:iron_helmet":2,"minecraft:wooden_pickaxe":1,"minecraft:baked_potato":40,"minecraft:birch_planks":212,"minecraft:pumpkin_seeds":28,"minecraft:dispenser":1,"minecraft:spruce_trapdoor":4,"minecraft:book":23,"minecraft:iron_chestplate":2,"minecraft:paper":264,"minecraft:diamond_pickaxe":1,"minecraft:charcoal":4,"minecraft:yellow_dye":12,"minecraft:shield":4,"minecraft:stick":2422,"minecraft:iron_ingot":406,"minecraft:leather_chestplate":2,"minecraft:stone_sword":10,"minecraft:gray_carpet":51,"minecraft:redstone_torch":5,"minecraft:light_gray_carpet":75,"minecraft:shears":1,"minecraft:polished_andesite":20,"minecraft:oak_door":6,"minecraft:fishing_rod":2,"minecraft:tripwire_hook":2,"minecraft:leather_boots":2,"minecraft:golden_chestplate":1,"minecraft:spruce_button":11,"minecraft:furnace":10,"minecraft:piston":1,"minecraft:oak_trapdoor":4,"minecraft:glass_pane":48,"minecraft:flint_and_steel":1,"minecraft:scaffolding":132,"minecraft:leather":1,"minecraft:iron_axe":4,"minecraft:iron_hoe":2,"minecraft:filled_map":3,"minecraft:gray_banner":1,"minecraft:observer":1,"minecraft:cooked_beef":85,"minecraft:sugar":21,"minecraft:red_dye":18,"minecraft:cooked_cod":1,"minecraft:diamond_sword":2,"minecraft:diorite_wall":18,"minecraft:iron_sword":6,"minecraft:bowl":4,"minecraft:cooked_salmon":12,"minecraft:bucket":1,"minecraft:stone_axe":9,"minecraft:bread":19,"minecraft:air":0,"minecraft:jungle_planks":68,"minecraft:blue_dye":7,"minecraft:oak_boat":3,"minecraft:white_dye":1,"minecraft:blue_wool":5,"minecraft:stonecutter":1,"minecraft:anvil":2,"minecraft:torch":528,"minecraft:lapis_block":3,"minecraft:carrot_on_a_stick":1},"minecraft:picked_up":{"minecraft:wooden_axe":1,"minecraft:iron_chestplate":5,"minecraft:lead":28,"minecraft:diamond_sword":9,"minecraft:enchanted_book":3,"minecraft:music_disc_cat":2,"minecraft:string":149,"minecraft:cooked_salmon":6,"minecraft:beetroot":20,"minecraft:spruce_planks":728,"minecraft:melon_slice":4,"minecraft:golden_helmet":2,"minecraft:spruce_pressure_plate":17,"minecraft:jukebox":1,"minecraft:composter":2,"minecraft:rabbit_foot":14,"minecraft:cauldron":1,"minecraft:stone_sword":39,"minecraft:light_gray_bed":10,"minecraft:birch_log":193,"minecraft:magma_block":18,"minecraft:feather":53,"minecraft:cooked_beef":108,"minecraft:water_bucket":1,"minecraft:jungle_log":17,"minecraft:flint":29,"minecraft:lantern":2,"minecraft:stonecutter":1,"minecraft:rabbit":8,"minecraft:glowstone_dust":161,"minecraft:dropper":4,"minecraft:stripped_spruce_log":26,"minecraft:ink_sac":23,"minecraft:loom":1,"minecraft:iron_hoe":10,"minecraft:polished_andesite":17,"minecraft:dispenser":5,"minecraft:lever":17,"minecraft:granite":384,"minecraft:spruce_button":16,"minecraft:bread":43,"minecraft:light_gray_carpet":60,"minecraft:dark_oak_fence":16,"minecraft:bricks":2,"minecraft:diamond_pickaxe":4,"minecraft:crafting_table":18,"minecraft:clay_ball":184,"minecraft:leather_leggings":10,"minecraft:cornflower":6,"minecraft:red_bed":17,"minecraft:flint_and_steel":4,"minecraft:white_carpet":29,"minecraft:compass":5,"minecraft:iron_shovel":3,"minecraft:glass_pane":54,"minecraft:cracked_stone_bricks":5,"minecraft:cartography_table":1,"minecraft:beef":157,"minecraft:spruce_slab":21,"minecraft:poppy":21,"minecraft:minecart":5,"minecraft:chest":19,"minecraft:birch_sapling":8,"minecraft:piston":2,"minecraft:egg":173,"minecraft:sandstone":53,"minecraft:oak_door":13,"minecraft:spruce_fence":18,"minecraft:white_dye":4,"minecraft:carrot":811,"minecraft:redstone":1221,"minecraft:prismarine_crystals":2,"minecraft:blue_carpet":13,"minecraft:stone_shovel":3,"minecraft:cooked_cod":4,"minecraft:beetroot_seeds":59,"minecraft:peony":7,"minecraft:gold_ingot":7,"minecraft:mutton":60,"minecraft:white_wool":62,"minecraft:rail":77,"minecraft:oxeye_daisy":15,"minecraft:stripped_oak_log":5,"minecraft:birch_leaves":48,"minecraft:tripwire_hook":5,"minecraft:yellow_dye":9,"minecraft:red_mushroom":7,"minecraft:filled_map":12,"minecraft:oak_log":641,"minecraft:lily_pad":1,"minecraft:golden_boots":1,"minecraft:paper":124,"minecraft:white_banner":9,"minecraft:stone_bricks":15,"minecraft:apple":29,"minecraft:kelp":129,"minecraft:stone_pickaxe":24,"minecraft:oak_fence_gate":7,"minecraft:iron_ore":461,"minecraft:glass_bottle":8,"minecraft:iron_sword":28,"minecraft:dark_oak_stairs":3,"minecraft:sweet_berries":183,"minecraft:daylight_detector":3,"minecraft:gravel":123,"minecraft:spruce_sapling":19,"minecraft:spruce_log":401,"minecraft:slime_ball":10,"minecraft:polished_diorite":3,"minecraft:stone_axe":13,"minecraft:painting":54,"minecraft:gray_wool":45,"minecraft:oak_button":6,"minecraft:baked_potato":27,"minecraft:ender_pearl":1,"minecraft:wheat":483,"minecraft:redstone_block":1,"minecraft:stone_brick_stairs":5,"minecraft:iron_leggings":4,"minecraft:oak_sign":24,"minecraft:bucket":4,"minecraft:red_dye":14,"minecraft:rose_bush":2,"minecraft:redstone_torch":5,"minecraft:cobblestone_slab":34,"minecraft:wooden_shovel":1,"minecraft:iron_pickaxe":18,"minecraft:iron_boots":3,"minecraft:furnace":13,"minecraft:blue_wool":2,"minecraft:tipped_arrow":2,"minecraft:stick":403,"minecraft:birch_trapdoor":4,"minecraft:oak_fence":114,"minecraft:torch":429,"minecraft:spruce_stairs":14,"minecraft:porkchop":24,"minecraft:dried_kelp":11,"minecraft:diorite":169,"minecraft:andesite_wall":9,"minecraft:rotten_flesh":198,"minecraft:obsidian":53,"minecraft:cod":17,"minecraft:cobblestone":6638,"minecraft:enchanting_table":2,"minecraft:leather_chestplate":10,"minecraft:lilac":1,"minecraft:repeater":3,"minecraft:andesite":769,"minecraft:potato":309,"minecraft:light_gray_dye":28,"minecraft:lapis_lazuli":163,"minecraft:dirt":4513,"minecraft:polished_granite":8,"minecraft:name_tag":2,"minecraft:leather_boots":1,"minecraft:glass":13,"minecraft:bone":131,"minecraft:bow":16,"minecraft:orange_tulip":1,"minecraft:wheat_seeds":1218,"minecraft:mossy_stone_bricks":10,"minecraft:bamboo":182,"minecraft:powered_rail":3,"minecraft:oak_planks":31,"minecraft:stone_hoe":9,"minecraft:diorite_wall":4,"minecraft:cooked_porkchop":30,"minecraft:poisonous_potato":4,"minecraft:sand":808,"minecraft:jungle_planks":12,"minecraft:jungle_slab":3,"minecraft:sugar":15,"minecraft:diamond":19,"minecraft:bone_meal":60,"minecraft:emerald":1,"minecraft:oak_sapling":51,"minecraft:netherrack":146,"minecraft:oak_leaves":11,"minecraft:fishing_rod":5,"minecraft:cocoa_beans":11,"minecraft:allium":2,"minecraft:azure_bluet":40,"minecraft:chicken":34,"minecraft:ladder":306,"minecraft:brown_mushroom":29,"minecraft:wooden_pickaxe":2,"minecraft:shield":9,"minecraft:oak_trapdoor":7,"minecraft:iron_axe":15,"minecraft:item_frame":4,"minecraft:blue_orchid":7,"minecraft:oak_boat":25,"minecraft:observer":3,"minecraft:light_gray_wool":54,"minecraft:sugar_cane":329,"minecraft:spruce_trapdoor":10,"minecraft:orange_dye":4,"minecraft:note_block":2,"minecraft:dark_oak_planks":9,"minecraft:arrow":250,"minecraft:jungle_stairs":4,"minecraft:saddle":2,"minecraft:salmon":40,"minecraft:leather":80,"minecraft:carrot_on_a_stick":4,"minecraft:birch_planks":32,"minecraft:cobblestone_stairs":32,"minecraft:gunpowder":60,"minecraft:cooked_mutton":36,"minecraft:gray_carpet":19,"minecraft:rabbit_hide":6,"minecraft:iron_ingot":37,"minecraft:cooked_chicken":30,"minecraft:book":49,"minecraft:scaffolding":15,"minecraft:pumpkin":27,"minecraft:birch_boat":1,"minecraft:chiseled_stone_bricks":1,"minecraft:quartz":75,"minecraft:dandelion":23,"minecraft:blast_furnace":1,"minecraft:white_bed":19,"minecraft:gold_ore":107,"minecraft:spruce_door":2,"minecraft:spider_eye":53,"minecraft:pumpkin_seeds":47,"minecraft:gray_banner":5,"minecraft:iron_helmet":7,"minecraft:coal":975,"minecraft:sunflower":3},"minecraft:broken":{"minecraft:iron_sword":1,"minecraft:stone_sword":2,"minecraft:stone_hoe":1,"minecraft:wooden_pickaxe":2,"minecraft:iron_axe":1,"minecraft:iron_pickaxe":22,"minecraft:iron_helmet":1,"minecraft:iron_shovel":2,"minecraft:stone_pickaxe":16,"minecraft:stone_axe":4,"minecraft:golden_pickaxe":1},"minecraft:killed":{"minecraft:cod":8,"minecraft:skeleton":60,"minecraft:chicken":33,"minecraft:magma_cube":1,"minecraft:salmon":32,"minecraft:pillager":9,"minecraft:donkey":1,"minecraft:zombie":80,"minecraft:cow":71,"minecraft:vindicator":1,"minecraft:ocelot":1,"minecraft:rabbit":13,"minecraft:ravager":1,"minecraft:polar_bear":3,"minecraft:enderman":1,"minecraft:witch":2,"minecraft:spider":54,"minecraft:pig":13,"minecraft:creeper":39,"minecraft:sheep":36,"minecraft:stray":3,"minecraft:slime":14,"minecraft:drowned":12,"minecraft:bat":10,"minecraft:squid":6},"minecraft:used":{"minecraft:beetroot":6,"minecraft:writable_book":11,"minecraft:dispenser":4,"minecraft:spruce_slab":15,"minecraft:ladder":167,"minecraft:chest":35,"minecraft:spruce_boat":3,"minecraft:lava_bucket":4,"minecraft:birch_sapling":5,"minecraft:diorite_wall":4,"minecraft:stone_brick_stairs":16,"minecraft:bow":82,"minecraft:sweet_berries":83,"minecraft:oak_sapling":40,"minecraft:furnace":21,"minecraft:cooked_cod":2,"minecraft:egg":89,"minecraft:gray_banner":5,"minecraft:potato":119,"minecraft:diorite":44,"minecraft:mossy_stone_bricks":7,"minecraft:spruce_door":10,"minecraft:powered_rail":7,"minecraft:wooden_pickaxe":120,"minecraft:composter":3,"minecraft:oak_leaves":11,"minecraft:sand":232,"minecraft:blast_furnace":1,"minecraft:pumpkin_seeds":22,"minecraft:polished_granite":50,"minecraft:diamond_sword":865,"minecraft:dark_oak_fence":9,"minecraft:smithing_table":1,"minecraft:oak_boat":23,"minecraft:oak_trapdoor":7,"minecraft:enchanting_table":3,"minecraft:stone_sword":703,"minecraft:light_gray_carpet":57,"minecraft:cooked_salmon":12,"minecraft:netherrack":35,"minecraft:torch":602,"minecraft:anvil":2,"minecraft:oak_fence_gate":12,"minecraft:polished_diorite":36,"minecraft:filled_map":7,"minecraft:iron_axe":771,"minecraft:spruce_button":16,"minecraft:melon_seeds":6,"minecraft:bamboo":34,"minecraft:tripwire_hook":7,"minecraft:glowstone":2,"minecraft:observer":2,"minecraft:wheat_seeds":475,"minecraft:water_bucket":51,"minecraft:lead":1,"minecraft:cartography_table":2,"minecraft:cauldron":3,"minecraft:spruce_fence_gate":2,"minecraft:cracked_stone_bricks":1,"minecraft:salmon":1,"minecraft:rail":39,"minecraft:crafting_table":26,"minecraft:red_bed":14,"minecraft:white_bed":15,"minecraft:campfire":1,"minecraft:spruce_log":1,"minecraft:diamond_pickaxe":1469,"minecraft:oxeye_daisy":1,"minecraft:oak_button":6,"minecraft:iron_pickaxe":6654,"minecraft:spruce_pressure_plate":22,"minecraft:spruce_trapdoor":6,"minecraft:spruce_sapling":11,"minecraft:blue_carpet":23,"minecraft:chiseled_stone_bricks":1,"minecraft:cobblestone":2682,"minecraft:potion":4,"minecraft:cooked_porkchop":25,"minecraft:glass_pane":14,"minecraft:dandelion":1,"minecraft:jukebox":1,"minecraft:iron_shovel":559,"minecraft:carrot_on_a_stick":4,"minecraft:oak_sign":27,"minecraft:iron_sword":815,"minecraft:carrot":299,"minecraft:obsidian":27,"minecraft:milk_bucket":2,"minecraft:glass":64,"minecraft:bricks":23,"minecraft:lantern":3,"minecraft:stone_bricks":182,"minecraft:item_frame":4,"minecraft:birch_trapdoor":10,"minecraft:repeater":3,"minecraft:redstone_lamp":1,"minecraft:magma_block":6,"minecraft:hay_block":2,"minecraft:written_book":9,"minecraft:scaffolding":19,"minecraft:jungle_button":1,"minecraft:beetroot_seeds":37,"minecraft:dropper":5,"minecraft:birch_leaves":47,"minecraft:stone_pickaxe":2522,"minecraft:gray_carpet":59,"minecraft:oak_planks":12,"minecraft:ender_pearl":1,"minecraft:sandstone":47,"minecraft:redstone_block":1,"minecraft:sugar_cane":27,"minecraft:loom":2,"minecraft:note_block":2,"minecraft:shears":69,"minecraft:redstone_torch":3,"minecraft:lever":17,"minecraft:daylight_detector":3,"minecraft:string":13,"minecraft:bread":14,"minecraft:iron_door":3,"minecraft:gravel":11,"minecraft:cooked_rabbit":6,"minecraft:andesite":227,"minecraft:golden_pickaxe":28,"minecraft:bone_meal":46,"minecraft:oak_fence":117,"minecraft:flint_and_steel":52,"minecraft:stone_shovel":51,"minecraft:redstone":286,"minecraft:dried_kelp":4,"minecraft:spruce_planks":90,"minecraft:wooden_shovel":78,"minecraft:stone_hoe":181,"minecraft:cooked_chicken":4,"minecraft:oak_door":17,"minecraft:dirt":2467,"minecraft:white_carpet":42,"minecraft:spruce_stairs":8,"minecraft:granite":64,"minecraft:spruce_fence":64,"minecraft:birch_door":1,"minecraft:andesite_wall":32,"minecraft:iron_hoe":157,"minecraft:bookshelf":14,"minecraft:minecart":4,"minecraft:cooked_beef":37,"minecraft:light_gray_bed":10,"minecraft:pumpkin":12,"minecraft:cooked_mutton":24,"minecraft:cobblestone_stairs":29,"minecraft:glass_bottle":4,"minecraft:polished_andesite":37,"minecraft:baked_potato":10,"minecraft:blue_wool":1,"minecraft:birch_boat":1,"minecraft:brown_mushroom":8,"minecraft:stonecutter":2,"minecraft:cobblestone_slab":37,"minecraft:music_disc_cat":2,"minecraft:painting":56,"minecraft:smoker":1,"minecraft:piston":2,"minecraft:apple":10,"minecraft:jungle_stairs":3,"minecraft:stone_axe":732,"minecraft:fishing_rod":18,"minecraft:white_banner":7,"minecraft:bucket":57,"minecraft:lapis_block":3,"minecraft:gray_wool":2},"minecraft:custom":{"minecraft:interact_with_crafting_table":641,"minecraft:bell_ring":6,"minecraft:leave_game":22,"minecraft:time_since_death":109641,"minecraft:damage_blocked_by_shield":4340,"minecraft:deaths":42,"minecraft:jump":20881,"minecraft:enchant_item":5,"minecraft:interact_with_furnace":366,"minecraft:play_record":2,"minecraft:traded_with_villager":19,"minecraft:interact_with_cartography_table":25,"minecraft:sleep_in_bed":173,"minecraft:damage_dealt":65026,"minecraft:interact_with_smoker":19,"minecraft:inspect_dispenser":2,"minecraft:horse_one_cm":55649,"minecraft:inspect_dropper":35,"minecraft:sneak_time":3545,"minecraft:interact_with_lectern":2,"minecraft:interact_with_blast_furnace":16,"minecraft:tune_noteblock":287,"minecraft:interact_with_stonecutter":28,"minecraft:time_since_rest":5685,"minecraft:swim_one_cm":894293,"minecraft:fly_one_cm":533153,"minecraft:open_chest":1809,"minecraft:fall_one_cm":223833,"minecraft:animals_bred":50,"minecraft:sprint_one_cm":2688643,"minecraft:drop":695,"minecraft:play_noteblock":15,"minecraft:talked_to_villager":136,"minecraft:walk_on_water_one_cm":632593,"minecraft:play_one_minute":4258079,"minecraft:interact_with_loom":34,"minecraft:crouch_one_cm":10688,"minecraft:mob_kills":510,"minecraft:fill_cauldron":2,"minecraft:interact_with_campfire":43,"minecraft:climb_one_cm":216824,"minecraft:walk_one_cm":16612509,"minecraft:walk_under_water_one_cm":565873,"minecraft:boat_one_cm":3805619,"minecraft:raid_trigger":1,"minecraft:damage_taken":24980,"minecraft:minecart_one_cm":30940}},"DataVersion":1968}